deepl_grpc/__init__.py
deepl_grpc/deepl_client.py
deepl_grpc/deepl_pb2.py
deepl_grpc/deepl_pb2_grpc.py
deepl_grpc/deepl_server.py
deepl_grpc/deepl_server.py.portalocker.lock
deepl_grpc-0.1.1.dist-info/WHEEL
deepl_grpc-0.1.1.dist-info/METADATA
deepl_grpc-0.1.1.dist-info/RECORD
