Metadata-Version: 2.1
Name: deepl-grpc
Version: 0.1.1
Summary: deepl grpc server and client
Home-page: https://github.com/ffreemt/deepl-grpc
License: MIT
Author: freemt
Requires-Python: >=3.7,<4.0
Classifier: License :: OSI Approved :: MIT License
Classifier: Programming Language :: Python :: 3
Classifier: Programming Language :: Python :: 3.7
Classifier: Programming Language :: Python :: 3.8
Requires-Dist: deepl-scraper-pp (>=0.1.1,<0.2.0)
Requires-Dist: google (>=3.0.0,<4.0.0)
Requires-Dist: grpcio (>=1.36.1,<2.0.0)
Requires-Dist: grpcio-reflection (>=1.36.1,<2.0.0)
Requires-Dist: grpcio-tools (>=1.36.1,<2.0.0)
Requires-Dist: logzero (>=1.6.3,<2.0.0)
Requires-Dist: portalocker (>=2.2.1,<3.0.0)
Requires-Dist: pysocks (>=1.7.1,<2.0.0)
Project-URL: Repository, https://github.com/ffreemt/deepl-grpc
